dragonfly/__init__.py
dragonfly/auth.py
dragonfly/constants.py
dragonfly/exceptions.py
dragonfly/request.py
dragonfly/response.py
dragonfly/utils.py
dragonfly/db/__init__.py
dragonfly/db/database.py
dragonfly/db/database_migrator.py
dragonfly/db/table.py
dragonfly/db/models/__init__.py
dragonfly/db/models/fields.py
dragonfly/db/models/model.py
dragonfly/db/models/relationships.py
dragonfly/middleware/__init__.py
dragonfly/middleware/middleware_controller.py
dragonfly/routes/__init__.py
dragonfly/routes/route_collection.py
dragonfly/routes/route_rule.py
dragonfly/routes/router.py
dragonfly/template/__init__.py
dragonfly/template/template.py
tests/__init__.py
tests/builder/__init__.py
tests/builder/builder.py
tests/builder/test_builder.py
tests/db/__init__.py
tests/db/test_database.py
tests/db/test_database_migrator.py
tests/db/test_model.py
tests/middleware/__init__.py
tests/middleware/all_middleware.py
tests/middleware/test_middleware.py
tests/middleware/test_middlware_controller.py
tests/routes/__init__.py
tests/routes/test_route_collection.py
tests/routes/test_route_rule.py
tests/routes/test_router.py
tests/routes/controllers/__init__.py
tests/routes/controllers/test_controller.py
dragonfly_web-1.0.dist-info/LICENSE
dragonfly_web-1.0.dist-info/METADATA
dragonfly_web-1.0.dist-info/WHEEL
dragonfly_web-1.0.dist-info/top_level.txt
dragonfly_web-1.0.dist-info/RECORD
