Metadata-Version: 2.1
Name: dragonfly-web
Version: 1.0
Summary: A web framework.
Home-page: https://github.com/MattJMLewis/dragonfly
Author: Matthew Lewis
Author-email: UNKNOWN
License: UNKNOWN
Platform: UNKNOWN
Classifier: Programming Language :: Python :: 3.7
